simnetpy/__init__.py
simnetpy/version.py
simnetpy/clustering/__init__.py
simnetpy/clustering/clustering.py
simnetpy/clustering/event_sampling.py
simnetpy/clustering/quality.py
simnetpy/clustering/spectral.py
simnetpy/datasets/__init__.py
simnetpy/datasets/distributions.py
simnetpy/datasets/multi_mod.py
simnetpy/datasets/single_mod.py
simnetpy/graph/__init__.py
simnetpy/graph/igraphf.py
simnetpy/graph/plotting.py
simnetpy/plotting/__init__.py
simnetpy/plotting/graph_plot.py
simnetpy/plotting/igraph_vis.py
simnetpy/similarity/__init__.py
simnetpy/similarity/merging.py
simnetpy/similarity/similarity.py
simnetpy/similarity/threshold.py
simnetpy/utils/__init__.py
simnetpy/utils/filesys.py
simnetpy/utils/plotting.py
simnetpy/utils/sci_funcs.py
simnetpy-0.3.1.dist-info/METADATA
simnetpy-0.3.1.dist-info/WHEEL
simnetpy-0.3.1.dist-info/licenses/AUTHORS.md
simnetpy-0.3.1.dist-info/licenses/LICENSE
simnetpy-0.3.1.dist-info/RECORD
