Metadata-Version: 2.3
Name: simnetpy
Version: 0.3.1
Summary: Python package for the Construction and Clustering of Similarity Networks
Project-URL: Download, https://github.com/amarnane/simnetpy
Project-URL: Homepage, https://github.com/amarnane/simnetpy
Project-URL: Documentation, https://amarnane.github.io/simnetpy/
Author-email: Aidan Marnane <aidan.marnane@gmail.com>
License-Expression: BSD-3-Clause
License-File: AUTHORS.md
License-File: LICENSE
Keywords: clustering,community-detection,graph-clustering,graphs,network-construction,networks,similarity-network
Classifier: Development Status :: 4 - Beta
Classifier: Intended Audience :: Science/Research
Classifier: License :: OSI Approved :: BSD License
Classifier: Programming Language :: Python :: 3
Classifier: Programming Language :: Python :: 3.8
Requires-Python: >=3.8
Requires-Dist: click
Requires-Dist: igraph==0.10.4
Requires-Dist: matplotlib
Requires-Dist: numpy
Requires-Dist: palettable
Requires-Dist: pandas
Requires-Dist: pyyaml
Requires-Dist: scikit-learn
Requires-Dist: scipy
Requires-Dist: seaborn
Requires-Dist: snfpy
Requires-Dist: spectralcluster
Requires-Dist: tqdm
Provides-Extra: dev
Requires-Dist: twine; extra == 'dev'
